{
  "nation": "Black River First Nation",
  "fiscal_year": "2021",
  "fiscal_year_end": "March 31, 2021",
  "province": "MB",
  "auditor": "MNP LLP",
  "audit_qualified": false,
  "going_concern": false,
  "one_time_items": true,
  "one_time_amount": 785035,
  "one_time_description": "Correction of an error reducing opening accumulated surplus by $785,035 (Note 22)",
  "population_on_reserve": 0,
  "population_total": 0,
  "num_subsidiaries": 1,
  "num_gbes": 1,
  "num_employees": 0,
  "num_housing_units": 0,
  "num_students_sponsored": 0,
  "num_businesses": 0,
  "unemployment_rate": 0,
  "economic_notes": "First Nation holds a 1/7 ownership interest in the South Beach Group of Partnerships (casino and hotel on Brokenhead Ojibway Nation land). Also a 12.5% beneficial owner of Shawano Wapunong Investments Corp. which invests in commercial real estate in Winnipeg. Demand loan of up to $4,669,000 taken to pursue legal claim against Government of Canada.",
  "revenue": 15182721,
  "expenses": 15693027,
  "annual_surplus": -1197951,
  "accumulated_surplus": 26374142,
  "isc_funding": 14946374,
  "total_government_transfers": 15990200,
  "osr": -807479,
  "prior_revenue": 13080092,
  "prior_expenses": 13989477,
  "prior_surplus": -568311,
  "prior_accumulated_surplus": 27572093,
  "cash": 6304084,
  "restricted_cash": 484640,
  "temporary_investments": 1107893,
  "accounts_receivable": 477132,
  "current_liabilities": 3811188,
  "deferred_revenue": 2087425,
  "long_term_debt": 6193709,
  "tangible_capital_assets": 31304576,
  "net_financial_assets": -5622946,
  "amortization": 2435109,
  "annual_debt_service": 400216,
  "expenses_health": 3909620,
  "expenses_education": 5603451,
  "expenses_housing": 1228623,
  "expenses_social": 1403777,
  "expenses_administration": 753544,
  "expenses_infrastructure": 2055319,
  "expenses_enterprises": 1122,
  "expenses_salaries_total": 2841574,
  "remuneration_chief_min": 0,
  "remuneration_chief_max": 0,
  "remuneration_council_min": 0,
  "remuneration_council_max": 0,
  "remuneration_staff_min": 0,
  "remuneration_staff_max": 0,
  "revenue_lines": {
    "Indigenous Services Canada (ISC)": 14946374,
    "Other revenue": 824465,
    "Assembly of Manitoba Chiefs": 621717,
    "Canada Mortgage and Housing Corporation": 365109,
    "Rent": 175817,
    "Tobacco tax rebates": 193704,
    "Manitoba Justice": 58000,
    "Revenue deferred in prior year": 84960,
    "Revenue deferred to subsequent year": -2087425,
    "Gain (loss) on investment in South Beach Group of Partnerships": -687645
  },
  "notes": "Fiscal year is 2021, not 2024. Audit includes Emphasis of Matter paragraph regarding demand loan payable taken to pursue legal claim against Government of Canada (max $4,669,000). Prior year figures are restated due to correction of an error (Note 22) reducing opening surplus by $785,035. Black River Development Corporation is fully consolidated. South Beach Group of Partnerships accounted for by modified equity method (1/7 interest). First Nation is not in compliance with CMHC replacement reserve requirements. OSR is negative because revenue deferred to subsequent year exceeds non-government revenue sources; total government transfers calculated as ISC $14,946,374 + CMHC $365,109 + Assembly of Manitoba Chiefs $621,717 + Manitoba Justice $58,000 = $15,991,200, with net deferred revenue adjustments making OSR effectively negative. expenses_housing combines Housing ($520,560) and Subsidized Housing ($708,063). expenses_salaries_total taken from cash flow statement cash paid to employees.",
  "working_capital_ratio": 2.2,
  "liquidity_ratio": 0.3,
  "ebitda_proxy": 1237158,
  "debt_service_coverage": 3.09,
  "net_assets_to_debt": 4.26,
  "revenue_growth": 16.08,
  "expense_growth": 12.18,
  "isc_dependency_pct": 98.44,
  "transfer_dependency_pct": 105.32,
  "osr_pct": -5.32,
  "adjusted_surplus": -1197950,
  "adjusted_ebitda": 1237159,
  "adjusted_dscr": 9.18,
  "health_score": 60,
  "warnings": [
    "One-time items ($1) represent 0.0% of revenue \u2014 surplus may not reflect ongoing operations",
    "High ISC dependency (98.44%) \u2014 operations heavily reliant on federal transfers"
  ]
}