{
  "nation": "Boothroyd Indian Band",
  "fiscal_year": "2024",
  "fiscal_year_end": "March 31, 2024",
  "province": "BC",
  "auditor": "Stolz CPA Inc.",
  "audit_qualified": false,
  "going_concern": false,
  "one_time_items": true,
  "one_time_amount": 509771,
  "one_time_description": "Correction of errors added to accumulated surplus at beginning of year (Note 15)",
  "population_on_reserve": 0,
  "population_total": 0,
  "num_subsidiaries": 1,
  "num_gbes": 4,
  "num_employees": 0,
  "num_housing_units": 0,
  "num_students_sponsored": 0,
  "num_businesses": 0,
  "unemployment_rate": 0,
  "economic_notes": "Nation has 20% interest in a choomEEnsh a Nlaka'pamux Limited Partnership (revenues $11.16M, net income $5.5M for year ended Dec 31, 2023). Also holds interests in Nlaka'pamux Resources Limited Partnership (17.9%) and related entities. Kahmoose Construction Inc. is a fully consolidated subsidiary.",
  "revenue": 9069794,
  "expenses": 6323427,
  "annual_surplus": 2746367,
  "accumulated_surplus": 12501390,
  "isc_funding": 3523316,
  "total_government_transfers": 5819667,
  "osr": 3250127,
  "prior_revenue": 6354417,
  "prior_expenses": 5229032,
  "prior_surplus": 1125385,
  "prior_accumulated_surplus": 9755023,
  "cash": 4275415,
  "restricted_cash": 461293,
  "temporary_investments": 45110,
  "accounts_receivable": 748591,
  "current_liabilities": 1025584,
  "deferred_revenue": 836074,
  "long_term_debt": 461434,
  "tangible_capital_assets": 6988392,
  "net_financial_assets": 5512120,
  "amortization": 507979,
  "annual_debt_service": 47415,
  "expenses_health": 1018557,
  "expenses_education": 661989,
  "expenses_housing": 764308,
  "expenses_social": 0,
  "expenses_administration": 548361,
  "expenses_infrastructure": 977341,
  "expenses_enterprises": 1060149,
  "expenses_salaries_total": 0,
  "remuneration_chief_min": 0,
  "remuneration_chief_max": 0,
  "remuneration_council_min": 0,
  "remuneration_council_max": 0,
  "remuneration_staff_min": 0,
  "remuneration_staff_max": 0,
  "revenue_lines": {
    "Indigenous Services Canada (ISC)": 3523316,
    "ISC revenue deferred": 215280,
    "Contracting income": 1287798,
    "Other income": 786040,
    "Province of British Columbia": 777697,
    "BC First Nations Gaming Revenue": 405372,
    "Fraser Thompson Indian Services Society": 270252,
    "Canada Mortgage and Housing Corporation": 232129,
    "First Nations Education Steering Committee": 125106,
    "Taxation": 121407,
    "First Nations Health Authority": 119340,
    "Rental income": 45168,
    "Fraser Health Authority": 30000,
    "Aboriginal Skills Employment and Training Strategy": 15965,
    "Interest income": 15755,
    "Earnings (loss) from Nation business entities": 1099169
  },
  "notes": "2023 comparatives restated due to correction of errors (Note 15) adding $509,771 to opening accumulated surplus. Nation business entities use December 31 year-end (fiscal lag). Restricted cash estimated as trust funds $419,484 + operating reserve $7,483 + replacement reserve $34,326 = $461,293. total_government_transfers calculated as ISC $3,523,316 + ISC deferred $215,280 + Province of BC $777,697 + Fraser Thompson Indian Services Society $270,252 + CMHC $232,129 + First Nations Education Steering Committee $125,106 + First Nations Health Authority $119,340 + Fraser Health Authority $30,000 + ASETS $15,965 + BC First Nations Gaming Revenue $405,372 + ISC revenue deferred already included = sum of government sources. osr includes contracting income, other income, taxation, rental income, interest income, and earnings from Nation business entities.",
  "working_capital_ratio": 5.39,
  "liquidity_ratio": 0.5,
  "ebitda_proxy": 3254346,
  "debt_service_coverage": 68.64,
  "net_assets_to_debt": 27.09,
  "revenue_growth": 42.73,
  "expense_growth": 20.93,
  "surplus_growth": 144.04,
  "isc_dependency_pct": 38.85,
  "transfer_dependency_pct": 64.17,
  "osr_pct": 35.83,
  "adjusted_surplus": 2746368,
  "adjusted_ebitda": 3254347,
  "adjusted_dscr": 79.35,
  "health_score": 95,
  "warnings": [
    "One-time items ($1) represent 0.0% of revenue \u2014 surplus may not reflect ongoing operations"
  ]
}