{
  "nation": "Chippewas of the Thames First Nation",
  "fiscal_year": "2021",
  "fiscal_year_end": "March 31, 2021",
  "province": "ON",
  "auditor": "MacNeill Edmundson Professional Corporation",
  "audit_qualified": true,
  "going_concern": false,
  "one_time_items": false,
  "one_time_amount": 0,
  "one_time_description": "",
  "population_on_reserve": 0,
  "population_total": 0,
  "num_subsidiaries": 2,
  "num_gbes": 0,
  "num_employees": 0,
  "num_housing_units": 0,
  "num_students_sponsored": 0,
  "num_businesses": 0,
  "unemployment_rate": 0,
  "economic_notes": "Investment in Garden Variety (retail cannabis stores in Manitoba, 6.5% ownership via 10552763 Canada Corp, total contributions $450,690). Development Corporation operates four solar farms. Green Lane Landfill revenue share agreement with City of Toronto (40% of tonnage royalties). Big Bear Creek Trust settlement funds (~$120M in investments). COVID-19 impacts noted.",
  "revenue": 30566131,
  "expenses": 27169982,
  "annual_surplus": 3396149,
  "accumulated_surplus": 31119211,
  "isc_funding": 9626247,
  "total_government_transfers": 22023062,
  "osr": 8543069,
  "prior_revenue": 28786425,
  "prior_expenses": 27287775,
  "prior_surplus": 1498650,
  "prior_accumulated_surplus": 27723062,
  "cash": 9501122,
  "restricted_cash": 0,
  "temporary_investments": 1867987,
  "accounts_receivable": 2133119,
  "current_liabilities": 1463933,
  "deferred_revenue": 5988981,
  "long_term_debt": 7120428,
  "tangible_capital_assets": 30205196,
  "net_financial_assets": 74831,
  "amortization": 1758886,
  "annual_debt_service": 618027,
  "expenses_health": 1903281,
  "expenses_education": 5245896,
  "expenses_housing": 1341194,
  "expenses_social": 4903268,
  "expenses_administration": 4433003,
  "expenses_infrastructure": 1139323,
  "expenses_enterprises": 182291,
  "expenses_salaries_total": 8692218,
  "remuneration_chief_min": 0,
  "remuneration_chief_max": 0,
  "remuneration_council_min": 0,
  "remuneration_council_max": 0,
  "remuneration_staff_min": 0,
  "remuneration_staff_max": 0,
  "revenue_lines": {
    "Indigenous Services Canada": 9626247,
    "Big Bear Creek transfers": 3967437,
    "Stepping Stones": 2871512,
    "Health Canada": 2652929,
    "Southern First Nations Secretariat": 2580921,
    "Province of Ontario": 2473888,
    "CMHC Rapid Housing Initiative": 1799245,
    "Other revenue": 1475152,
    "Ontario First Nations Limited Partnership": 1444987,
    "Union of Ontario Indians": 797472,
    "Rent revenue": 512155,
    "CMHC subsidy": 293570,
    "Green Lane landfill revenue share": 474021,
    "Band generated": 366054,
    "Unrealized gains (losses) on investments": 303999,
    "Foreign exchange gain (loss)": 126274,
    "Investment income": 58863,
    "Interest": 33389,
    "CMHC housing repair funding": 26802,
    "Deferred revenue - prior year": 4415286,
    "Deferred revenue - current year": -5988981
  },
  "notes": "Audit is QUALIFIED: Development Corporation (wholly-owned subsidiary) financials for 2019, 2020, and 2021 were not available; only 2018 audited figures (by another firm) are included in consolidation. Prior year figures restated for three items: (A) ISC Fourplex funding receivable correction -$262,584; (B) Big Bear Creek community development income understatement +$285,933; (C) Province of Ontario tobacco project revenue +$180,000. Big Bear Creek Trust (~$120M) and Land Claim Trust are administered trusts not on balance sheet. Development Corporation has outstanding demand loan of $2,056,302 at prime+1.5%. total_government_transfers estimated as ISC + Big Bear Creek + Stepping Stones + Health Canada + Southern First Nations Secretariat + Province of Ontario + CMHC Rapid Housing Initiative + CMHC subsidy + Union of Ontario Indians + CMHC housing repair funding. OSR = total revenue minus estimated government transfers.",
  "working_capital_ratio": 9.22,
  "liquidity_ratio": 0.39,
  "ebitda_proxy": 5155035,
  "debt_service_coverage": 8.34,
  "net_assets_to_debt": 4.37,
  "revenue_growth": 6.18,
  "expense_growth": -0.43,
  "surplus_growth": 126.61,
  "isc_dependency_pct": 31.49,
  "transfer_dependency_pct": 72.05,
  "osr_pct": 27.95,
  "health_score": 75,
  "warnings": [
    "Qualified audit opinion issued \u2014 financial statements may not fully reflect true position"
  ]
}