{
  "nation": "Chippewas of Georgina Island First Nation",
  "fiscal_year": "2024",
  "fiscal_year_end": "March 31, 2024",
  "province": "ON",
  "auditor": "Rumley Holmes LLP",
  "audit_qualified": false,
  "going_concern": false,
  "one_time_items": false,
  "one_time_amount": 0,
  "one_time_description": "",
  "population_on_reserve": 0,
  "population_total": 0,
  "num_subsidiaries": 8,
  "num_gbes": 0,
  "num_employees": 0,
  "num_housing_units": 0,
  "num_students_sponsored": 0,
  "num_businesses": 0,
  "unemployment_rate": 0,
  "economic_notes": "Entities consolidated include Coldwater Narrows Trust, Virginia Beach Marina, Nish Radio Inc., 2458582 Ontario Limited (Island View Business Centre), Goin Fuel Company Limited, 6832067 Canada Inc., 2697365 Ontario Limited (Hadden Road Developments), and Williams Treaty Trust. Additional unaudited schedules cover Daawegamig Lodge, Tobacco Trails, Williams Treaty Settlement, Per Capita Distribution Fund, Trust Revenue Fund, OFNLP Revenue, and IVBC Property Management Inc.",
  "revenue": 74998606,
  "expenses": 60635125,
  "annual_surplus": 14363481,
  "accumulated_surplus": 270112780,
  "isc_funding": 20276970,
  "total_government_transfers": 24782189,
  "osr": 50216417,
  "prior_revenue": 63600868,
  "prior_expenses": 57039625,
  "prior_surplus": 6561243,
  "prior_accumulated_surplus": 246753762,
  "cash": 41391204,
  "restricted_cash": 0,
  "temporary_investments": 180133837,
  "accounts_receivable": 6334933,
  "current_liabilities": 6499719,
  "deferred_revenue": 19713222,
  "long_term_debt": 6940383,
  "tangible_capital_assets": 69630326,
  "net_financial_assets": 195975733,
  "amortization": 4443274,
  "annual_debt_service": 0,
  "expenses_health": 0,
  "expenses_education": 0,
  "expenses_housing": 271040,
  "expenses_social": 0,
  "expenses_administration": 0,
  "expenses_infrastructure": 0,
  "expenses_enterprises": 0,
  "expenses_salaries_total": 0,
  "remuneration_chief_min": 0,
  "remuneration_chief_max": 0,
  "remuneration_council_min": 0,
  "remuneration_council_max": 0,
  "remuneration_staff_min": 0,
  "remuneration_staff_max": 0,
  "revenue_lines": {
    "Health Canada": 567341,
    "CMHC": 157478,
    "Indigenous Services Canada": 20276970,
    "Province of Ontario": 3780400,
    "Land leases and fees": 1255747,
    "Ontario First Nations Land Partnership (OFNLP)": 1230925,
    "Interest": 3665668,
    "Dividend": 1574166,
    "Taxation": 1087848,
    "Other": 39125129,
    "Gain (loss) on sale of investments": 2276934
  },
  "notes": "Complex consolidation including trusts (Coldwater Narrows Trust, Williams Treaty Trust) and multiple commercial entities. Large portfolio investments of $180M. Significant deferred revenue increase from $8.8M to $19.7M. Long-term debt increased substantially from $2.1M to $6.9M. Remuneration schedules not visible in provided pages. Total government transfers calculated as Health Canada + CMHC + ISC + Province of Ontario = $24,782,189. OSR includes land leases, OFNLP, interest, dividends, taxation, other revenue, and investment gains.",
  "working_capital_ratio": 35.06,
  "liquidity_ratio": 2.95,
  "ebitda_proxy": 18806755,
  "net_assets_to_debt": 38.92,
  "revenue_growth": 17.92,
  "expense_growth": 6.3,
  "surplus_growth": 118.91,
  "isc_dependency_pct": 27.04,
  "transfer_dependency_pct": 33.04,
  "osr_pct": 66.96,
  "health_score": 80,
  "warnings": []
}