{
  "nation": "Conseil des Anicinapek de Kitcisakik",
  "fiscal_year": "2022",
  "fiscal_year_end": "March 31, 2022",
  "province": "QC",
  "auditor": "Raymond Chabot Grant Thornton",
  "audit_qualified": false,
  "going_concern": false,
  "one_time_items": false,
  "one_time_amount": 0,
  "one_time_description": "",
  "population_on_reserve": 0,
  "population_total": 0,
  "num_subsidiaries": 0,
  "num_gbes": 0,
  "num_employees": 0,
  "num_housing_units": 0,
  "num_students_sponsored": 0,
  "num_businesses": 0,
  "unemployment_rate": 0,
  "economic_notes": "Nation has investments in Cooperative de Solidarite Wenicec (10 preferred shares) and Projet Nadagam (32% interest). Forestry sector active. Community sector businesses include depanneur, catering service, tourist project, artisan project. CSEF (Centre de savoirs etre savoir faire) operates as separate segment.",
  "revenue": 22340909,
  "expenses": 16833850,
  "annual_surplus": 1836255,
  "accumulated_surplus": 10040871,
  "isc_funding": 9467649,
  "total_government_transfers": 18588694,
  "osr": 3752215,
  "prior_revenue": 20874614,
  "prior_expenses": 14241607,
  "prior_surplus": 2479395,
  "prior_accumulated_surplus": 8204616,
  "cash": 11278668,
  "restricted_cash": 23132,
  "temporary_investments": 2000000,
  "accounts_receivable": 5091656,
  "current_liabilities": 12549683,
  "deferred_revenue": 10311992,
  "long_term_debt": 354742,
  "tangible_capital_assets": 7998197,
  "net_financial_assets": -1647939,
  "amortization": 1071152,
  "annual_debt_service": 78651,
  "expenses_health": 5937259,
  "expenses_education": 3675029,
  "expenses_housing": 0,
  "expenses_social": 1107890,
  "expenses_administration": 2670113,
  "expenses_infrastructure": 1733851,
  "expenses_enterprises": 0,
  "expenses_salaries_total": 9218269,
  "remuneration_chief_min": 0,
  "remuneration_chief_max": 0,
  "remuneration_council_min": 0,
  "remuneration_council_max": 0,
  "remuneration_staff_min": 0,
  "remuneration_staff_max": 0,
  "revenue_lines": {
    "Entente de transferts financiers (SAC)": 4130596,
    "Paiements de contribution fixes (SAC)": 4133977,
    "Paiements de contribution souples (SAC)": 1203076,
    "Secretariat aux affaires autochtones": 256457,
    "Direction generale de la sante des Premieres Nations et des Inuits - Entente": 6194799,
    "Direction generale de la sante des Premieres Nations et des Inuits - Recouvrements": 26539,
    "Conseil de la Nation Waban-Aki": 51456,
    "Conseil en Education des Premieres Nations": 812553,
    "CISSSAT - Entente": 467285,
    "C.S.S.S.P.N.Q.L": 187542,
    "Gouvernement provincial - Entente": 1382876,
    "Gouvernement provincial - Remboursements": -93394,
    "Gouvernement federal - Entente": 861565,
    "FRC": 196917,
    "FAE": 107877,
    "FRC-J": 22391,
    "PCC": 97638,
    "Regional / Local autres": 11300,
    "Revenus contrats et services des secteurs de la communaute": 1197374,
    "Revenus de contrats et services": 110835,
    "Frais communautaires": 74124,
    "Revenus de donateurs": 27860,
    "Revenus de garderie": 12570,
    "Interets et frais d'administration": 44309,
    "Interets - Fonds affecte en fiducie": 360,
    "Autres revenus": 105599,
    "Remboursements - Commission de credit": 26092,
    "Redevances": 595672
  },
  "notes": "Financial statements in French. Fiscal year end March 31, 2022. Net financial assets reported as net debt of -1,647,939 (negative = net debt position). Revenue total of 22,340,909 is gross before deferred revenue adjustments; net revenue recognized is 18,670,105 after prior year deferred revenue brought in and current year deferrals. Government transfers total calculated from sectoral disclosure: federal 16,581,069 + provincial 2,007,625 = 18,588,694. OSR calculated as 22,340,909 minus 18,588,694 = 3,752,215. Accumulated surplus equals total fund balances of 10,040,871. Remuneration of chief and councillors totalled 211,346 but individual ranges not provided. Large deferred revenue balance of 10,311,992 represents significant unspent program funding. Royalties (redevances) of 595,672 in 2022 vs 1,583,467 in 2021 - significant decline. The statement uses fund accounting with four funds: administration, reserve, capital assets, and trust.",
  "working_capital_ratio": 1.47,
  "liquidity_ratio": 0.26,
  "ebitda_proxy": 2907407,
  "debt_service_coverage": 36.97,
  "net_assets_to_debt": 28.3,
  "revenue_growth": 7.02,
  "expense_growth": 18.2,
  "surplus_growth": -25.94,
  "isc_dependency_pct": 42.38,
  "transfer_dependency_pct": 83.2,
  "osr_pct": 16.8,
  "health_score": 72,
  "warnings": []
}