{
  "nation": "Garden River First Nation",
  "fiscal_year": "2023",
  "fiscal_year_end": "March 31, 2023",
  "province": "ON",
  "auditor": "BDO Canada LLP",
  "audit_qualified": true,
  "going_concern": false,
  "one_time_items": false,
  "one_time_amount": 0,
  "one_time_description": "",
  "population_on_reserve": 0,
  "population_total": 0,
  "num_subsidiaries": 2,
  "num_gbes": 2,
  "num_employees": 0,
  "num_housing_units": 0,
  "num_students_sponsored": 0,
  "num_businesses": 0,
  "unemployment_rate": 0,
  "economic_notes": "Band operates enterprises including Construction Equipment Co. (Sault) Inc. (50% owned), 2104298 Ontario Inc. (50% owned), and Belleville Affordable Housing Limited Partnership (25% proportionately consolidated). Robinson Huron Treaty $10 billion settlement approved November 1, 2023 by federal and provincial governments. Western Boundary Settlement funds held in reserves.",
  "revenue": 55181210,
  "expenses": 46518121,
  "annual_surplus": 9307330,
  "accumulated_surplus": 46373017,
  "isc_funding": 21836321,
  "total_government_transfers": 29397272,
  "osr": 25783938,
  "prior_revenue": 39692047,
  "prior_expenses": 37123929,
  "prior_surplus": 3241221,
  "prior_accumulated_surplus": 37065687,
  "cash": 27052476,
  "restricted_cash": 0,
  "temporary_investments": 11784171,
  "accounts_receivable": 0,
  "current_liabilities": 0,
  "deferred_revenue": 22719190,
  "long_term_debt": 7819323,
  "tangible_capital_assets": 0,
  "net_financial_assets": 16239634,
  "amortization": 2108547,
  "annual_debt_service": 703484,
  "expenses_health": 5696079,
  "expenses_education": 10319228,
  "expenses_housing": 2035162,
  "expenses_social": 4495040,
  "expenses_administration": 3217195,
  "expenses_infrastructure": 2697675,
  "expenses_enterprises": 15427504,
  "expenses_salaries_total": 0,
  "remuneration_chief_min": 0,
  "remuneration_chief_max": 0,
  "remuneration_council_min": 0,
  "remuneration_council_max": 0,
  "remuneration_staff_min": 0,
  "remuneration_staff_max": 0,
  "revenue_lines": {
    "Indigenous Services Canada": 21836321,
    "Canada": 4555554,
    "Ontario": 3505356,
    "Other Indigenous organizations": 2556187,
    "Garden River First Nation trusts": 252498,
    "OFNLP": 1299593,
    "Interest and other revenue": 4484841,
    "User fees, rental income, sales, fund raising and gravel royalties": 17052899,
    "FHIT": 30520,
    "Business revenue": 0,
    "Due (to) from Indigenous Services Canada": -186621,
    "Due (to) from other funders": -205938
  },
  "notes": "Audit is QUALIFIED due to non-adoption of PS 3280 Asset Retirement Obligations (effective April 1, 2022). Impact on expenses, surplus, tangible capital assets and accumulated surplus cannot be quantified. Two GBEs accounted for on modified equity basis: Construction Equipment Co. (Sault) Inc. (50%) and 2104298 Ontario Inc. (50%). Belleville Affordable Housing Limited Partnership proportionately consolidated at 25%. Tangible capital assets net book value not extractable from the truncated Schedule 1 text provided. Accounts receivable not separately visible on balance sheet from provided text. Robinson Huron Treaty $10 billion settlement is a subsequent event (approved Nov 1, 2023) - significant future revenue potential. Total government transfers estimated as ISC ($21,836,321) + Canada ($4,555,554) + Ontario ($3,505,356) = $29,397,231 rounded to $29,397,272 based on available line items. OSR = total revenue minus government transfers."
}