{
  "nation": "Hollow Water First Nation",
  "fiscal_year": "2021",
  "fiscal_year_end": "March 31, 2021",
  "province": "MB",
  "auditor": "Baker Tilly HMA LLP",
  "audit_qualified": true,
  "going_concern": false,
  "one_time_items": false,
  "one_time_amount": 0,
  "one_time_description": "",
  "population_on_reserve": 0,
  "population_total": 0,
  "num_subsidiaries": 3,
  "num_gbes": 2,
  "num_employees": 0,
  "num_housing_units": 0,
  "num_students_sponsored": 0,
  "num_businesses": 0,
  "unemployment_rate": 0,
  "economic_notes": "First Nation holds a one-seventh ownership in South Beach Casino Limited Partnership (casino and hotel on Brokenhead Ojibway Nation land at Scanterbury, MB). Also holds 51% of Hollow Water-WERI Construction Ltd. (proportionate consolidation). Wanipigaa-Sibi Development Corporation fully consolidated.",
  "revenue": 15083817,
  "expenses": 17952837,
  "annual_surplus": -2869020,
  "accumulated_surplus": 24578937,
  "isc_funding": 9792703,
  "total_government_transfers": 13902523,
  "osr": 1181294,
  "prior_revenue": 16249370,
  "prior_expenses": 15190022,
  "prior_surplus": 1059348,
  "prior_accumulated_surplus": 27447957,
  "cash": 2730263,
  "restricted_cash": 427865,
  "temporary_investments": 204400,
  "accounts_receivable": 2383612,
  "current_liabilities": 2839097,
  "deferred_revenue": 2712867,
  "long_term_debt": 7155758,
  "tangible_capital_assets": 30630779,
  "net_financial_assets": -6289291,
  "amortization": 1296128,
  "annual_debt_service": 298571,
  "expenses_health": 2985628,
  "expenses_education": 4518801,
  "expenses_housing": 2112273,
  "expenses_social": 1191915,
  "expenses_administration": 3291940,
  "expenses_infrastructure": 818066,
  "expenses_enterprises": 287797,
  "expenses_salaries_total": 3867562,
  "remuneration_chief_min": 0,
  "remuneration_chief_max": 0,
  "remuneration_council_min": 0,
  "remuneration_council_max": 0,
  "remuneration_staff_min": 0,
  "remuneration_staff_max": 0,
  "revenue_lines": {
    "Indigenous Services Canada": 9792703,
    "Health Canada": 3767051,
    "Canada Mortgage and Housing Corporation": 335769,
    "Province of Manitoba": 179186,
    "Southeast Resource Development Council Corporation": 354977,
    "Government of Canada - Department of Justice": 135013,
    "Manitoba Hydro": 42158,
    "Income from Government Business Partnership": 770000,
    "Administration revenue": 174187,
    "Rent": 184493,
    "Tobacco tax rebate": 32474,
    "GST and sales tax rebates": 8131,
    "Ottawa Trust interest": 426,
    "Assembly of Manitoba Chiefs": 347588,
    "Other": 1424335,
    "Revenue deferred in prior year": 1060351,
    "Revenue deferred to subsequent year": -2712867
  },
  "notes": "Audit is QUALIFIED due to unavailability of accounting records for Hollow Water-WERI Construction Ltd. (51% owned). Auditor's report dated March 31, 2023 \u2014 approximately two years after fiscal year end. Budget information not provided and omitted from financial statements, noted as departure from PSA standards. South Beach Casino LP investment declined significantly (loss of $687,835 vs income of $607,542 prior year). Demand loan of $1,169,501 for legal claim against Government of Canada. CMHC replacement reserve underfunded by $249,088. expenses_enterprises combines SIBI Development Corporation ($6,170) and Hollow Water-WERI Construction Ltd. ($281,627). total_government_transfers includes ISC $9,792,703 + Health Canada $3,767,051 + CMHC $335,769 + net deferred adjustments (-$1,652,516) + Province of Manitoba $179,186 + Dept of Justice $135,013 + Southeast Resource Dev Council $354,977 + Assembly of Manitoba Chiefs $347,588 + Manitoba Hydro $42,158 = approximately $13,301,929 before deferred; using gross government transfer lines: ISC+Health Canada+CMHC+Province+Dept Justice+SRDC+AMC+Manitoba Hydro = 14,954,481 gross; osr calculated as total revenue minus gross government transfers."
}