{
  "nation": "Little Grand Rapids First Nation",
  "fiscal_year": "2024",
  "fiscal_year_end": "March 31, 2024",
  "province": "MB",
  "auditor": "Baker Tilly HMA LLP",
  "audit_qualified": false,
  "going_concern": false,
  "one_time_items": false,
  "one_time_amount": 0,
  "one_time_description": "",
  "population_on_reserve": 0,
  "population_total": 0,
  "num_subsidiaries": 0,
  "num_gbes": 0,
  "num_employees": 0,
  "num_housing_units": 0,
  "num_students_sponsored": 0,
  "num_businesses": 0,
  "unemployment_rate": 0,
  "economic_notes": "CMHC housing mortgages of $5,084,128 (22% of total liabilities) partially subsidized annually. CMHC subsidies received: $341,701 in 2024. Shelter allowance rents collected: $132,877 in 2024. Annual CMHC loan payments approximately $440,000. Unexpended ISC funding balance of $8,860,655 to be reported as revenue in 2024/25. Capital projects included school construction, 6-unit housing, lagoon, holding tank installations, skid steer purchase, CMHC Rapid Housing Initiative units.",
  "revenue": 43702438,
  "expenses": 39446467,
  "annual_surplus": 4255971,
  "accumulated_surplus": 98770196,
  "isc_funding": 28911508,
  "total_government_transfers": 0,
  "osr": 0,
  "prior_revenue": 40450345,
  "prior_expenses": 37049328,
  "prior_surplus": 3401017,
  "prior_accumulated_surplus": 94514225,
  "cash": 0,
  "restricted_cash": 26567,
  "temporary_investments": 3689421,
  "accounts_receivable": 0,
  "current_liabilities": 13534804,
  "deferred_revenue": 0,
  "long_term_debt": 9446254,
  "tangible_capital_assets": 0,
  "net_financial_assets": 1653074,
  "amortization": 0,
  "annual_debt_service": 0,
  "expenses_health": 0,
  "expenses_education": 0,
  "expenses_housing": 0,
  "expenses_social": 0,
  "expenses_administration": 0,
  "expenses_infrastructure": 0,
  "expenses_enterprises": 0,
  "expenses_salaries_total": 0,
  "remuneration_chief_min": 0,
  "remuneration_chief_max": 0,
  "remuneration_council_min": 0,
  "remuneration_council_max": 0,
  "remuneration_staff_min": 0,
  "remuneration_staff_max": 0,
  "revenue_lines": {
    "ISC Revenue": 28911508
  },
  "notes": "This document is a management letter only, not the full consolidated financial statements. Key financial figures extracted from summary tables within the letter. Total financial assets: $24,634,132. Total liabilities: $22,981,058. Net financial assets (net assets): $1,653,074. Long-term debt portion: $9,446,254 (CMHC mortgages $5,084,128 included). Working capital ratio: 154.55%. Sustainability ratio: 91.02%. Replacement reserve fund balance: $1,130,797, funded with only $2,600 cash \u2014 shortfall of $1,128,197. Accumulated surplus of $98,770,196 likely includes tangible capital assets; detailed balance sheet not provided. Total government transfers and OSR cannot be determined from this document alone."
}