{
  "nation": "Samson Cree Nation",
  "fiscal_year": "2024",
  "revenue": 128278401,
  "expenses": 144537735,
  "annual_surplus": 111960184,
  "accumulated_surplus": 742263599,
  "cash": 153234388,
  "restricted_cash": 0,
  "temporary_investments": 0,
  "accounts_receivable": 9673898,
  "current_liabilities": 74320646,
  "government_transfers_repayable": 0,
  "deferred_revenue": 64872193,
  "long_term_debt": 12240365,
  "total_assets": 895704179,
  "net_financial_assets": 683735877,
  "amortization": 6069161,
  "isc_funding": 43313043,
  "total_government_transfers": 58406115,
  "osr": 70000000,
  "prior_revenue": 134109363,
  "prior_expenses": 121873031,
  "prior_surplus": 6975589,
  "prior_accumulated_surplus": 630303415,
  "annual_debt_service": 15590357,
  "one_time_items": 134000000,
  "audit_qualified": true,
  "notes": "Qualified audit opinion. $134M settlement distorts 2024 surplus. Peace Hills Trust excluded.",
  "working_capital_ratio": 2.19,
  "liquidity_ratio": 0.69,
  "ebitda_proxy": 118029345,
  "debt_service_coverage": 7.57,
  "net_assets_to_debt": 60.64,
  "revenue_growth": -4.35,
  "expense_growth": 18.6,
  "surplus_growth": 1505.03,
  "isc_dependency_pct": 33.76,
  "transfer_dependency_pct": 45.53,
  "osr_pct": 54.57,
  "adjusted_surplus": -22039816,
  "health_score": 80,
  "warnings": [
    "One-time items ($134,000,000) represent 104.5% of revenue \u2014 surplus may not reflect ongoing operations",
    "Excluding one-time items, underlying operations show a deficit of $22,039,816",
    "Qualified audit opinion issued \u2014 financial statements may not fully reflect true position"
  ]
}