{
  "nation": "Sunchild First Nation",
  "fiscal_year": "2022",
  "fiscal_year_end": "March 31, 2022",
  "province": "AB",
  "auditor": "Doyle & Company Chartered Professional Accountants",
  "audit_qualified": false,
  "going_concern": false,
  "one_time_items": false,
  "one_time_amount": 0,
  "one_time_description": "",
  "population_on_reserve": 0,
  "population_total": 0,
  "num_subsidiaries": 0,
  "num_gbes": 5,
  "num_employees": 0,
  "num_housing_units": 0,
  "num_students_sponsored": 0,
  "num_businesses": 5,
  "unemployment_rate": 0,
  "economic_notes": "Five nation-controlled business entities accounted for by modified equity method: Sunchild Construction GP Ltd., Sunchild Gravel GP Ltd., Sunchild Oil & Gas Ltd., Sunchild Utilities Limited Partnership, Sunchild Business Development Corp. Trust funds held for Agricultural Benefits and Treaty Land Entitlement claims litigation.",
  "revenue": 38854589,
  "expenses": 29104327,
  "annual_surplus": -2150473,
  "accumulated_surplus": 43821993,
  "isc_funding": 27271086,
  "total_government_transfers": 32481076,
  "osr": 6373513,
  "prior_revenue": 30682139,
  "prior_expenses": 26306736,
  "prior_surplus": -4310376,
  "prior_accumulated_surplus": 37466406,
  "cash": 7239825,
  "restricted_cash": 25,
  "temporary_investments": 974710,
  "accounts_receivable": 1160466,
  "current_liabilities": 2810229,
  "deferred_revenue": 8526256,
  "long_term_debt": 625812,
  "tangible_capital_assets": 44657221,
  "net_financial_assets": -835228,
  "amortization": 2735894,
  "annual_debt_service": 200000,
  "expenses_health": 4577707,
  "expenses_education": 6944800,
  "expenses_housing": 1392113,
  "expenses_social": 2950311,
  "expenses_administration": 3304099,
  "expenses_infrastructure": 2514475,
  "expenses_enterprises": 0,
  "expenses_salaries_total": 9643107,
  "remuneration_chief_min": 0,
  "remuneration_chief_max": 0,
  "remuneration_council_min": 0,
  "remuneration_council_max": 0,
  "remuneration_staff_min": 0,
  "remuneration_staff_max": 0,
  "revenue_lines": {
    "Indigenous Services Canada (ISC)": 27271086,
    "Health Canada": 4986994,
    "Indigenous Skills and Employment Training Strategy": 223396,
    "Trust Funds - Capital": 2099061,
    "First Nation Development Fund (FNDF)": 479022,
    "Other revenue": 6833723,
    "Deferred contributions from previous period": 5487563,
    "Deferred contributions to subsequent period": -8526256
  },
  "notes": "Fiscal year is March 31, 2022 (not 2024). Five government business enterprises accounted for by modified equity method (not consolidated). Net loss of $2,150,473 after tangible capital asset expenditures of $9,034,298. Promissory note of $2,284,032 owing to Minister of Crown-Indigenous Relations for Agricultural Benefits and Treaty Land Entitlement claims negotiation, interest-free unless in default. Trust funds - Other of $452,665 held with a law firm for litigation. Annual debt service represents repayment of demand loan only ($200,000); long-term debt obtained in current year ($625,812 CIBC mortgage). ISC funding notably higher than prior year ($27.3M vs $22.0M). expenses_education estimated as sum of all School lines plus ISET program. expenses_housing includes Housing and Band Owned Housing Administration. expenses_infrastructure includes Public Works and Public Works-Other. expenses_social includes Social Services, Social Development Service Delivery Administration, and Community Wellbeing Initiatives. No schedule of remuneration included in statements. total_government_transfers estimated as ISC + Health Canada + ISET = $32,481,076; osr calculated as total revenue minus government transfers."
}