{
  "nation": "Tahltan Indian Band",
  "fiscal_year": "2022",
  "fiscal_year_end": "March 31, 2022",
  "province": "BC",
  "auditor": "BDO Canada LLP",
  "audit_qualified": true,
  "going_concern": false,
  "one_time_items": false,
  "one_time_amount": 0,
  "one_time_description": "",
  "population_on_reserve": 0,
  "population_total": 0,
  "num_subsidiaries": 2,
  "num_gbes": 5,
  "num_employees": 0,
  "num_housing_units": 0,
  "num_students_sponsored": 0,
  "num_businesses": 0,
  "unemployment_rate": 0,
  "economic_notes": "TNDLP has joint venture agreements providing construction and support services. TBDC operates grocery store, gas bar, motel and restaurant in Telegraph Creek BC. Tahltan Heritage Trust holds monies from resource developers using natural resources in traditional territory.",
  "revenue": 20070294,
  "expenses": 11914240,
  "annual_surplus": 14436867,
  "accumulated_surplus": 48147661,
  "isc_funding": 10723863,
  "total_government_transfers": 14823457,
  "osr": 5246837,
  "prior_revenue": 16943364,
  "prior_expenses": 10895586,
  "prior_surplus": 8997536,
  "prior_accumulated_surplus": 33714493,
  "cash": 10448748,
  "restricted_cash": 977933,
  "temporary_investments": 0,
  "accounts_receivable": 4856707,
  "current_liabilities": 3246192,
  "deferred_revenue": 160659,
  "long_term_debt": 953941,
  "tangible_capital_assets": 19713032,
  "net_financial_assets": 28431997,
  "amortization": 1218030,
  "annual_debt_service": 197077,
  "expenses_health": 2443962,
  "expenses_education": 858865,
  "expenses_housing": 772571,
  "expenses_social": 1530578,
  "expenses_administration": 2409888,
  "expenses_infrastructure": 524985,
  "expenses_enterprises": 0,
  "expenses_salaries_total": 0,
  "remuneration_chief_min": 0,
  "remuneration_chief_max": 0,
  "remuneration_council_min": 0,
  "remuneration_council_max": 0,
  "remuneration_staff_min": 0,
  "remuneration_staff_max": 0,
  "revenue_lines": {
    "Indigenous Services Canada (ISC)": 10723863,
    "First Nations Health Authority (FNHA)": 3376964,
    "Department of Fisheries and Oceans Canada": 3700,
    "Canada Mortgage and Housing Corporation (CMHC)": 32053,
    "Ottawa Trust": 8994,
    "Ministry of Forests, Lands and Natural Resources": 15020,
    "Ministry of Children and Family Development": 353003,
    "Ministry of Justice": 285904,
    "Northern Health Authority": 0,
    "Insurance proceeds": 161640,
    "BCFN Gaming Revenue Sharing LP": 570115,
    "Donations and other income": 1621172,
    "Rental income": 903414,
    "Tahltan Central Government": 1000000,
    "Stikine Wholistic Working Group (SWWG)": 488572,
    "Canada Post": 264948,
    "Aboriginal Housing Management Association (AHMA)": 164374,
    "First Nations Education Steering Committee (FNESC)": 42558,
    "Debt forgiveness": 54000,
    "Income from long-term investments": 6279442,
    "Gain on disposal of tangible capital assets": 1371
  },
  "notes": "Qualified audit opinion due to: (1) Stikine River Song Cafe/General Store Ltd. and Tahltan Centre Ltd. recorded using modified equity method instead of full consolidation as required by PSAS; (2) Unable to conclude on accounting treatment for 33.3% interests in TNDLP, TNDC, and Tahltan Legacy Corporation; (3) 33.3% interest in Tahltan Heritage Trust recorded at cost but auditors unable to determine if portfolio investment or shared control partnership; (4) Capital asset listing includes pre-2015 opening balances that could not be sufficiently audited. Band does not prepare a budget so no budgeted figures presented. Accumulated surplus on balance sheet ($48,147,661) differs slightly from statement of operations ending figure ($48,151,360) \u2014 likely a rounding or presentation difference."
}