{
  "nation": "Witchekan Lake First Nation",
  "fiscal_year": "2020",
  "fiscal_year_end": "March 31, 2020",
  "province": "SK",
  "auditor": "Grant Thornton LLP",
  "audit_qualified": true,
  "going_concern": false,
  "one_time_items": false,
  "one_time_amount": 0,
  "one_time_description": "",
  "population_on_reserve": 0,
  "population_total": 0,
  "num_subsidiaries": 1,
  "num_gbes": 2,
  "num_employees": 0,
  "num_housing_units": 0,
  "num_students_sponsored": 0,
  "num_businesses": 0,
  "unemployment_rate": 0,
  "economic_notes": "First Nation owns 33.3% of A.C. Forestry Ltd. and 33.3% of A.C. Realty Ltd. (government business enterprises). COVID-19 impacted operations including office closures, travel restrictions, and cancellation of events. First Nations Trust gaming revenues expected to be negatively impacted by temporary closure of Saskatchewan Indian Gaming Authority casinos.",
  "revenue": 13376545,
  "expenses": 9289194,
  "annual_surplus": 4087351,
  "accumulated_surplus": 23095461,
  "isc_funding": 9889619,
  "total_government_transfers": 11322762,
  "osr": 2053783,
  "prior_revenue": 9426247,
  "prior_expenses": 8430045,
  "prior_surplus": 996202,
  "prior_accumulated_surplus": 19008110,
  "cash": 200320,
  "restricted_cash": 1164133,
  "temporary_investments": 482369,
  "accounts_receivable": 1245618,
  "current_liabilities": 739373,
  "deferred_revenue": 1473906,
  "long_term_debt": 3728583,
  "tangible_capital_assets": 25931326,
  "net_financial_assets": -2835865,
  "amortization": 989507,
  "annual_debt_service": 193299,
  "expenses_health": 801415,
  "expenses_education": 2877256,
  "expenses_housing": 665407,
  "expenses_social": 1266192,
  "expenses_administration": 1380136,
  "expenses_infrastructure": 228168,
  "expenses_enterprises": 0,
  "expenses_salaries_total": 2977097,
  "remuneration_chief_min": 0,
  "remuneration_chief_max": 0,
  "remuneration_council_min": 0,
  "remuneration_council_max": 0,
  "remuneration_staff_min": 0,
  "remuneration_staff_max": 0,
  "revenue_lines": {
    "Indigenous Services Canada": 9889619,
    "Agency Chiefs Child and Family Services": 771024,
    "Canadian Mortgage and Housing Corporation": 329984,
    "Land leases": 505109,
    "Other revenue": 445589,
    "Agency Chiefs Tribal Council": 432779,
    "A.C. Forestry": 261664,
    "Saskatchewan Indian Gaming Authority": 232955,
    "Rent": 221694,
    "Community Development Corporation": 146118,
    "National Health & Welfare": 122156,
    "Interest": 17854
  },
  "notes": "Audit is qualified for two reasons: (1) auditors were denied access to financial information of A.C. Forestry Ltd. and A.C. Realty Ltd. (33.3% owned GBEs), so carrying value is nil and revenue of $261,664 from A.C. Forestry is included but unverified; (2) no budget was prepared or approved by Chief and Council for the fiscal year, which is a departure from PSAS. Comparative 2019 figures were restated due to prior period adjustments including reclassification of restricted cash, correction to accounts receivable from trust funds, and correction to investment accounting. CMHC housing consolidated as subsidiary. No remuneration schedule included in the financial statements provided. Restricted cash of $1,027,584 for capital projects and $136,549 for CMHC reserves totalling $1,164,133. Total government transfers calculated as ISC $9,889,619 + CMHC $329,984 + Agency Chiefs Child and Family Services $771,024 + National Health and Welfare $122,156 + Agency Chiefs Tribal Council $432,779 = $11,545,562 less ISC recovered funding note suggests net ISC is already $9,889,619; total_government_transfers set to ISC + CMHC + ACFS + NHW + ACTC = 11545562 but adjusted to reflect only transfers from governments. OSR includes land leases, rent, A.C. Forestry, SIGA, Community Development Corporation, interest, and other revenue."
}