{
  "nation": "Wuskwi Sipihk First Nation",
  "fiscal_year": "2020",
  "fiscal_year_end": "March 31, 2020",
  "province": "MB",
  "auditor": "MNP LLP",
  "audit_qualified": false,
  "going_concern": false,
  "one_time_items": false,
  "one_time_amount": 0,
  "one_time_description": "",
  "population_on_reserve": 0,
  "population_total": 0,
  "num_subsidiaries": 11,
  "num_gbes": 6,
  "num_employees": 0,
  "num_housing_units": 0,
  "num_students_sponsored": 0,
  "num_businesses": 0,
  "unemployment_rate": 0,
  "economic_notes": "First Nation has investments in Aseneskak Casino Limited Partnership (16.67%), Mahihkan Bus Lines Limited Partnership (16.67%), and Nekote Limited Partnership (14.29%). Major capital projects underway: new school ($10.6M contract), new water treatment plant (~$9.3M contract), new lagoon (~$5.7M contract). Previously under third-party management for ISC and health programs, exited August/September 2018.",
  "revenue": 16928447,
  "expenses": 8218853,
  "annual_surplus": 8848521,
  "accumulated_surplus": 19583865,
  "isc_funding": 17860238,
  "total_government_transfers": 20229804,
  "osr": 2878165,
  "prior_revenue": 10993041,
  "prior_expenses": 7854200,
  "prior_surplus": 3359172,
  "prior_accumulated_surplus": 10735344,
  "cash": 819612,
  "restricted_cash": 6930577,
  "temporary_investments": 0,
  "accounts_receivable": 751503,
  "current_liabilities": 1031895,
  "deferred_revenue": 8426720,
  "long_term_debt": 3376588,
  "tangible_capital_assets": 0,
  "net_financial_assets": -3782375,
  "amortization": 705460,
  "annual_debt_service": 468905,
  "expenses_health": 1842355,
  "expenses_education": 22093,
  "expenses_housing": 0,
  "expenses_social": 0,
  "expenses_administration": 1477464,
  "expenses_infrastructure": 0,
  "expenses_enterprises": 1543527,
  "expenses_salaries_total": 0,
  "remuneration_chief_min": 0,
  "remuneration_chief_max": 0,
  "remuneration_council_min": 0,
  "remuneration_council_max": 0,
  "remuneration_staff_min": 0,
  "remuneration_staff_max": 0,
  "revenue_lines": {
    "Indigenous Services Canada": 17860238,
    "Employment and Social Development Canada": 149922,
    "Health Canada": 2152972,
    "Canada Mortgage and Housing Corporation": 66672,
    "Gas Bar sales": 1392210,
    "Video Lottery Terminals": 125019,
    "User fees": 19892,
    "Rental income": 107947,
    "Manitoba Hydro": 91730,
    "Other revenue": 1084588,
    "Deferred revenue from the prior year": 2555839,
    "Deferred revenue to following year": -8420593,
    "Earnings (loss) from investment in Nation partnerships": -239850,
    "Repayment of funding": -18139,
    "Fuel tax rebates": 52709,
    "Tobacco tax rebates": 86218
  },
  "notes": "Fiscal year 2020 (ended March 31, 2020). Nation was previously under third-party management for ISC and health programs, fully exited by October 2018. Large deferred revenue balance of $8.4M primarily from capital projects (new school, water treatment plant, lagoon). Restricted cash of $6.93M held for capital construction projects. Net book value of tangible capital assets not extractable from text (Schedule 1 referenced but not provided). Six entities accounted for under modified equity method (GBEs). Eleven departments/entities fully consolidated. No remuneration schedule provided in extracted text."
}